aciclean.py
aciclean-0.1.7.dist-info/LICENSE
aciclean-0.1.7.dist-info/METADATA
aciclean-0.1.7.dist-info/WHEEL
aciclean-0.1.7.dist-info/entry_points.txt
aciclean-0.1.7.dist-info/top_level.txt
aciclean-0.1.7.dist-info/RECORD
