Metadata-Version: 2.1
Name: aciclean
Version: 0.1.7
Summary: ACIClean is a tool that helps you clean up your Cisco ACI infrastructure by detecting and reporting on unused objects.
Author-email: Oliver Fueckert <oliver@cubinet.de>
License-File: LICENSE
Requires-Dist: click
Provides-Extra: dev
Requires-Dist: build ; extra == 'dev'
Provides-Extra: sdk
